py_multi_3xui/__init__.py
py_multi_3xui/exceptions/__init__.py
py_multi_3xui/exceptions/exceptions.py
py_multi_3xui/managers/__init__.py
py_multi_3xui/managers/auth_cookie_manager.py
py_multi_3xui/managers/servers_manager.py
py_multi_3xui/server/__init__.py
py_multi_3xui/server/server.py
py_multi_3xui/tools/__init__.py
py_multi_3xui/tools/converter.py
py_multi_3xui/tools/enums.py
py_multi_3xui/tools/generator.py
py_multi_3xui/tools/regular_expressions.py
py_multi_3xui-1.2.2.dist-info/licenses/LICENSE
py_multi_3xui-1.2.2.dist-info/METADATA
py_multi_3xui-1.2.2.dist-info/WHEEL
py_multi_3xui-1.2.2.dist-info/top_level.txt
py_multi_3xui-1.2.2.dist-info/RECORD
