Metadata-Version: 2.4
Name: py_multi_3xui
Version: 1.2.2
Summary: module for managing multiple 3x-ui panels
Author-email: Dmeetrogon <dmeetrogon@egmail.com>
Project-URL: Homepage, https://github.com/Dmeetrogon/py_multi_3xui
Project-URL: Issues, https://github.com/Dmeetrogon/py_multi_3xui/issues
Keywords: vpn,3x-ui,vless,reality,vless+reality,x-ui,SDK,py3xui,x-ui,proxy
Classifier: Programming Language :: Python :: 3.11
Classifier: Programming Language :: Python :: 3.12
Classifier: Operating System :: OS Independent
Classifier: License :: OSI Approved :: MIT License
Requires-Python: >=3.8
License-File: LICENSE
Requires-Dist: py3xui>=0.5.1
Requires-Dist: diskcache>=5.6.3
Requires-Dist: pyotp>=2.9.0
Dynamic: license-file
